pypimirror/__init__.py
pypimirror/__main__.py
pypimirror/mirror.py
pypimirror_simple-0.1.0a1.dist-info/DESCRIPTION.rst
pypimirror_simple-0.1.0a1.dist-info/METADATA
pypimirror_simple-0.1.0a1.dist-info/RECORD
pypimirror_simple-0.1.0a1.dist-info/WHEEL
pypimirror_simple-0.1.0a1.dist-info/entry_points.txt
pypimirror_simple-0.1.0a1.dist-info/metadata.json
pypimirror_simple-0.1.0a1.dist-info/top_level.txt
