Metadata-Version: 2.0
Name: pypimirror-simple
Version: 0.1.0a1
Summary: A simple pypimirror
Home-page: UNKNOWN
Author: wilypomegranate
Author-email: wilypomegranate@users.noreply.github.com>
License: UNKNOWN
Platform: UNKNOWN
Classifier: Development Status :: 5 - Production/Stable
Classifier: Environment :: Console
Classifier: Intended Audience :: Developers
Classifier: Intended Audience :: System Administrators
Classifier: Operating System :: Unix
Classifier: Operating System :: POSIX
Classifier: Programming Language :: Python
Classifier: Programming Language :: Python :: 2.7
Classifier: Topic :: System :: Systems Administration
Requires-Dist: beautifulsoup4 (==4.4.1)
Requires-Dist: requests (==2.9.1)
